{
  "bankroll": 657.7000000000003,
  "initial_bankroll": 1000.0,
  "trade_counter": 15,
  "trades": [
    {
      "trade_id": "PT-0001",
      "market_id": "2029573",
      "question": "NYC 2026-04-22 \u2014 62-63\u00b0F",
      "side": "YES",
      "entry_price": 0.014,
      "shares": 1315.4828,
      "dollar_amount": 18.42,
      "estimated_probability": 0.12749327586419862,
      "market_price_at_entry": 0.014,
      "edge_at_entry": 0.11349327586419862,
      "confidence": 0.8,
      "timestamp": "2026-04-21T22:52:40.190744+00:00",
      "status": "OPEN",
      "exit_price": null,
      "resolution": null,
      "pnl": 0.0,
      "strategy_tag": "",
      "model_tag": ""
    },
    {
      "trade_id": "PT-0002",
      "market_id": "2029780",
      "question": "Beijing 2026-04-22 \u2014 22\u00b0C",
      "side": "YES",
      "entry_price": 0.0925,
      "shares": 383.7495,
      "dollar_amount": 35.5,
      "estimated_probability": 0.29761173426486875,
      "market_price_at_entry": 0.0925,
      "edge_at_entry": 0.20511173426486876,
      "confidence": 0.8,
      "timestamp": "2026-04-21T22:52:40.192470+00:00",
      "status": "RESOLVED_LOSS",
      "exit_price": null,
      "resolution": false,
      "pnl": -35.5,
      "strategy_tag": "",
      "model_tag": ""
    },
    {
      "trade_id": "PT-0003",
      "market_id": "2040252",
      "question": "NYC 2026-04-23 \u2014 64-65\u00b0F",
      "side": "YES",
      "entry_price": 0.021,
      "shares": 820.107,
      "dollar_amount": 17.22,
      "estimated_probability": 0.14829654208496157,
      "market_price_at_entry": 0.021,
      "edge_at_entry": 0.12729654208496158,
      "confidence": 0.7000000000000001,
      "timestamp": "2026-04-21T22:52:40.194852+00:00",
      "status": "OPEN",
      "exit_price": null,
      "resolution": null,
      "pnl": 0.0,
      "strategy_tag": "",
      "model_tag": ""
    },
    {
      "trade_id": "PT-0004",
      "market_id": "2040253",
      "question": "NYC 2026-04-23 \u2014 66-67\u00b0F",
      "side": "YES",
      "entry_price": 0.08,
      "shares": 181.5581,
      "dollar_amount": 14.52,
      "estimated_probability": 0.1827578585361325,
      "market_price_at_entry": 0.08,
      "edge_at_entry": 0.1027578585361325,
      "confidence": 0.7000000000000001,
      "timestamp": "2026-04-21T22:52:40.195630+00:00",
      "status": "OPEN",
      "exit_price": null,
      "resolution": null,
      "pnl": 0.0,
      "strategy_tag": "",
      "model_tag": ""
    },
    {
      "trade_id": "PT-0005",
      "market_id": "2040460",
      "question": "Beijing 2026-04-23 \u2014 23\u00b0C",
      "side": "YES",
      "entry_price": 0.0805,
      "shares": 347.8051,
      "dollar_amount": 28.0,
      "estimated_probability": 0.28161656748360325,
      "market_price_at_entry": 0.0805,
      "edge_at_entry": 0.20111656748360324,
      "confidence": 0.7000000000000001,
      "timestamp": "2026-04-21T22:52:40.197636+00:00",
      "status": "OPEN",
      "exit_price": null,
      "resolution": null,
      "pnl": 0.0,
      "strategy_tag": "",
      "model_tag": ""
    },
    {
      "trade_id": "PT-0006",
      "market_id": "2040459",
      "question": "Beijing 2026-04-23 \u2014 22\u00b0C or below",
      "side": "YES",
      "entry_price": 0.0125,
      "shares": 1564.0333,
      "dollar_amount": 19.55,
      "estimated_probability": 0.16808392221631302,
      "market_price_at_entry": 0.0125,
      "edge_at_entry": 0.155583922216313,
      "confidence": 0.7000000000000001,
      "timestamp": "2026-04-21T22:52:40.198491+00:00",
      "status": "OPEN",
      "exit_price": null,
      "resolution": null,
      "pnl": 0.0,
      "strategy_tag": "",
      "model_tag": ""
    },
    {
      "trade_id": "PT-0007",
      "market_id": "2029572",
      "question": "NYC 2026-04-22 \u2014 60-61\u00b0F",
      "side": "YES",
      "entry_price": 0.0155,
      "shares": 2051.155,
      "dollar_amount": 31.79,
      "estimated_probability": 0.21611319886952093,
      "market_price_at_entry": 0.0155,
      "edge_at_entry": 0.20061319886952095,
      "confidence": 0.9,
      "timestamp": "2026-04-22T04:02:36.766590+00:00",
      "status": "OPEN",
      "exit_price": null,
      "resolution": null,
      "pnl": 0.0,
      "strategy_tag": "",
      "model_tag": ""
    },
    {
      "trade_id": "PT-0008",
      "market_id": "2029571",
      "question": "NYC 2026-04-22 \u2014 58-59\u00b0F",
      "side": "YES",
      "entry_price": 0.095,
      "shares": 207.1261,
      "dollar_amount": 19.68,
      "estimated_probability": 0.21348084161971145,
      "market_price_at_entry": 0.095,
      "edge_at_entry": 0.11848084161971145,
      "confidence": 0.9,
      "timestamp": "2026-04-22T04:02:36.767731+00:00",
      "status": "OPEN",
      "exit_price": null,
      "resolution": null,
      "pnl": 0.0,
      "strategy_tag": "",
      "model_tag": ""
    },
    {
      "trade_id": "PT-0009",
      "market_id": "2029781",
      "question": "Beijing 2026-04-22 \u2014 23\u00b0C",
      "side": "YES",
      "entry_price": 0.135,
      "shares": 228.988,
      "dollar_amount": 30.91,
      "estimated_probability": 0.3172057310101143,
      "market_price_at_entry": 0.135,
      "edge_at_entry": 0.18220573101011428,
      "confidence": 0.9,
      "timestamp": "2026-04-22T04:02:36.770194+00:00",
      "status": "OPEN",
      "exit_price": null,
      "resolution": null,
      "pnl": 0.0,
      "strategy_tag": "",
      "model_tag": ""
    },
    {
      "trade_id": "PT-0010",
      "market_id": "2040524",
      "question": "Denver 2026-04-23 \u2014 68\u00b0F or higher",
      "side": "YES",
      "entry_price": 0.145,
      "shares": 344.83197348291685,
      "dollar_amount": 50,
      "estimated_probability": 0.99999999999982,
      "market_price_at_entry": 0.145,
      "edge_at_entry": 0.85499999999982,
      "confidence": 0.9,
      "timestamp": "2026-04-22T04:02:36.774465+00:00",
      "status": "OPEN",
      "exit_price": null,
      "resolution": null,
      "pnl": 0.0,
      "strategy_tag": "",
      "model_tag": ""
    },
    {
      "trade_id": "PT-0011",
      "market_id": "2029597",
      "question": "Atlanta 2026-04-22 \u2014 84-85\u00b0F",
      "side": "YES",
      "entry_price": 0.105,
      "shares": 158.6988,
      "dollar_amount": 16.66,
      "estimated_probability": 0.2178171012892181,
      "market_price_at_entry": 0.105,
      "edge_at_entry": 0.11281710128921811,
      "confidence": 0.9,
      "timestamp": "2026-04-22T10:02:57.404814+00:00",
      "status": "OPEN",
      "exit_price": null,
      "resolution": null,
      "pnl": 0.0,
      "strategy_tag": "",
      "model_tag": ""
    },
    {
      "trade_id": "PT-0012",
      "market_id": "2040461",
      "question": "Beijing 2026-04-23 \u2014 24\u00b0C",
      "side": "YES",
      "entry_price": 0.155,
      "shares": 97.3827,
      "dollar_amount": 15.09,
      "estimated_probability": 0.26606497935986206,
      "market_price_at_entry": 0.155,
      "edge_at_entry": 0.11106497935986206,
      "confidence": 0.8,
      "timestamp": "2026-04-22T10:02:57.409791+00:00",
      "status": "OPEN",
      "exit_price": null,
      "resolution": null,
      "pnl": 0.0,
      "strategy_tag": "",
      "model_tag": ""
    },
    {
      "trade_id": "PT-0013",
      "market_id": "2040520",
      "question": "Denver 2026-04-23 \u2014 60-61\u00b0F",
      "side": "YES",
      "entry_price": 0.0415,
      "shares": 386.782,
      "dollar_amount": 16.05,
      "estimated_probability": 0.17834889746642002,
      "market_price_at_entry": 0.0415,
      "edge_at_entry": 0.13684889746642,
      "confidence": 0.8,
      "timestamp": "2026-04-22T10:02:57.411506+00:00",
      "status": "OPEN",
      "exit_price": null,
      "resolution": null,
      "pnl": 0.0,
      "strategy_tag": "",
      "model_tag": ""
    },
    {
      "trade_id": "PT-0014",
      "market_id": "2049453",
      "question": "NYC 2026-04-24 \u2014 66\u00b0F or higher",
      "side": "YES",
      "entry_price": 0.1,
      "shares": 192.5854,
      "dollar_amount": 19.26,
      "estimated_probability": 0.2803132928965834,
      "market_price_at_entry": 0.1,
      "edge_at_entry": 0.1803132928965834,
      "confidence": 0.7000000000000001,
      "timestamp": "2026-04-22T10:02:57.414059+00:00",
      "status": "OPEN",
      "exit_price": null,
      "resolution": null,
      "pnl": 0.0,
      "strategy_tag": "",
      "model_tag": ""
    },
    {
      "trade_id": "PT-0015",
      "market_id": "2049452",
      "question": "NYC 2026-04-24 \u2014 64-65\u00b0F",
      "side": "YES",
      "entry_price": 0.09,
      "shares": 107.192,
      "dollar_amount": 9.65,
      "estimated_probability": 0.18396465776333243,
      "market_price_at_entry": 0.09,
      "edge_at_entry": 0.09396465776333243,
      "confidence": 0.7000000000000001,
      "timestamp": "2026-04-22T10:02:57.415421+00:00",
      "status": "OPEN",
      "exit_price": null,
      "resolution": null,
      "pnl": 0.0,
      "strategy_tag": "",
      "model_tag": ""
    }
  ],
  "calibration": [
    {
      "predicted": 0.29761173426486875,
      "actual": 0,
      "market_id": "2029780",
      "time": "2026-04-22T10:02:08.998040+00:00"
    }
  ]
}